COPYING
MANIFEST.in
README
setup.py
dates/__init__.py
dates/dates.py
dates.egg-info/PKG-INFO
dates.egg-info/SOURCES.txt
dates.egg-info/dependency_links.txt
dates.egg-info/entry_points.txt
dates.egg-info/requires.txt
dates.egg-info/top_level.txt