Metadata-Version: 1.0
Name: dates
Version: 0.0.1
Summary: A small tool based on python-dateutil that just prints dates
Home-page: https://github.com/chmduquesne/dates
Author: Christophe-Marie Duquesne
Author-email: chm.duquesne@gmail.com
License: Redistribution and use in source and binary forms, with or without modification,
